lusid_drive/__init__.py
lusid_drive/__version__.py
lusid_drive/api_client.py
lusid_drive/configuration.py
lusid_drive/exceptions.py
lusid_drive/rest.py
lusid_drive/api/__init__.py
lusid_drive/api/application_metadata_api.py
lusid_drive/api/files_api.py
lusid_drive/api/folders_api.py
lusid_drive/api/search_api.py
lusid_drive/models/__init__.py
lusid_drive/models/access_controlled_action.py
lusid_drive/models/access_controlled_resource.py
lusid_drive/models/action_id.py
lusid_drive/models/create_folder.py
lusid_drive/models/id_selector_definition.py
lusid_drive/models/identifier_part_schema.py
lusid_drive/models/link.py
lusid_drive/models/lusid_problem_details.py
lusid_drive/models/lusid_validation_problem_details.py
lusid_drive/models/paged_resource_list_of_storage_object.py
lusid_drive/models/resource_list_of_access_controlled_resource.py
lusid_drive/models/search_body.py
lusid_drive/models/storage_object.py
lusid_drive/models/update_file.py
lusid_drive/models/update_folder.py
lusid_drive/tcp/__init__.py
lusid_drive/tcp/tcp_keep_alive_probes.py
lusid_drive/utilities/__init__.py
lusid_drive/utilities/api_client_builder.py
lusid_drive/utilities/api_client_factory.py
lusid_drive/utilities/api_configuration.py
lusid_drive/utilities/api_configuration_loader.py
lusid_drive/utilities/config_keys.json
lusid_drive/utilities/file_streaming.py
lusid_drive/utilities/folders_api_extensions.py
lusid_drive/utilities/lusid_drive_retry.py
lusid_drive/utilities/proxy_config.py
lusid_drive/utilities/refreshing_token.py
lusid_drive/utilities/utility_functions.py
lusid_drive/utilities/wait_for_virus_scan.py
lusid_drive_sdk_preview-0.1.672.dist-info/METADATA
lusid_drive_sdk_preview-0.1.672.dist-info/WHEEL
lusid_drive_sdk_preview-0.1.672.dist-info/top_level.txt
lusid_drive_sdk_preview-0.1.672.dist-info/RECORD
