Metadata-Version: 2.1
Name: lusid-drive-sdk-preview
Version: 0.1.672
Summary: Python SDK Preview for LUSID Drive API
Home-page: https://github.com/finbourne/drive-sdk-python-preview
Author: FINBOURNE Technology
Author-email: engineering@finbourne.com
License: MIT
Keywords: OpenAPI,FINBOURNE,LUSID,LUSID Drive API
Platform: UNKNOWN
Requires-Dist: six (>=1.10)
Requires-Dist: certifi (>=14.05.14)
Requires-Dist: python-dateutil (>=2.5.3)
Requires-Dist: urllib3 (>=1.15.1)
Requires-Dist: requests (>=2.21.0)
